newsmodel/__init__.py
newsmodel/utils.py
newsmodel/dataloader/__init__.py
newsmodel/dataloader/dataloader.py
newsmodel/inference/__init__.py
newsmodel/inference/inference.py
newsmodel/model/__init__.py
newsmodel/model/model.py
newsmodel/preprocess/__init__.py
newsmodel/preprocess/_ner.py
newsmodel/preprocess/_textrank.py
newsmodel/preprocess/countryset.py
newsmodel/preprocess/preprocessing.py
newsmodel/trainer/__init__.py
newsmodel/trainer/nlp_model.py
newsmodel-0.28.dist-info/METADATA
newsmodel-0.28.dist-info/WHEEL
newsmodel-0.28.dist-info/top_level.txt
newsmodel-0.28.dist-info/RECORD
