Metadata-Version: 2.1
Name: newsmodel
Version: 0.28
Summary: Tacademy project의 newsmodel을 학습하고 실험하기 위한 패키지 입니다.
Home-page: https://github.com/JuwonOh/Tacademy-project
Download-URL: https://github.com/JuwonOh/Tacademy-project/tree/main/NewsModel
Author: Juwon Oh, Jinho Han
Author-email: 13a71032776@gmail.com
License: MIT License
Platform: UNKNOWN
Classifier: Programming Language :: Python :: 3
Classifier: License :: OSI Approved :: MIT License
Classifier: Operating System :: OS Independent
Requires-Python: >=3.8
Requires-Dist: torch (>=1.8.2+cpu)
Requires-Dist: mlflow (>=1.24.0)
Requires-Dist: scikit-learn (>=1.0.2)
Requires-Dist: transformers (>=4.16.2)
Requires-Dist: nltk
Requires-Dist: progressbar
